README.md
setup.cfg
setup.py
keras_maskrcnn/__init__.py
keras_maskrcnn/losses.py
keras_maskrcnn.egg-info/PKG-INFO
keras_maskrcnn.egg-info/SOURCES.txt
keras_maskrcnn.egg-info/dependency_links.txt
keras_maskrcnn.egg-info/entry_points.txt
keras_maskrcnn.egg-info/requires.txt
keras_maskrcnn.egg-info/top_level.txt
keras_maskrcnn/backend/__init__.py
keras_maskrcnn/backend/cntk_backend.py
keras_maskrcnn/backend/common.py
keras_maskrcnn/backend/dynamic.py
keras_maskrcnn/backend/tensorflow_backend.py
keras_maskrcnn/backend/theano_backend.py
keras_maskrcnn/bin/__init__.py
keras_maskrcnn/bin/debug.py
keras_maskrcnn/bin/evaluate.py
keras_maskrcnn/bin/train.py
keras_maskrcnn/callbacks/__init__.py
keras_maskrcnn/callbacks/coco.py
keras_maskrcnn/callbacks/eval.py
keras_maskrcnn/layers/__init__.py
keras_maskrcnn/layers/foo.py
keras_maskrcnn/layers/misc.py
keras_maskrcnn/layers/roi.py
keras_maskrcnn/layers/upsample.py
keras_maskrcnn/models/__init__.py
keras_maskrcnn/models/resnet.py
keras_maskrcnn/models/retinanet.py
keras_maskrcnn/preprocessing/__init__.py
keras_maskrcnn/preprocessing/coco.py
keras_maskrcnn/preprocessing/csv_generator.py
keras_maskrcnn/preprocessing/generator.py
keras_maskrcnn/utils/__init__.py
keras_maskrcnn/utils/coco_eval.py
keras_maskrcnn/utils/eval.py
keras_maskrcnn/utils/overlap.py
keras_maskrcnn/utils/visualization.py