Metadata-Version: 1.2
Name: keras-maskrcnn
Version: 0.2.1
Summary: Keras implementation of MaskRCNN instance aware segmentation.
Home-page: https://github.com/fizyr/keras-maskrcnn
Maintainer: Hans Gaiser
Maintainer-email: h.gaiser@fizyr.com
License: UNKNOWN
Platform: UNKNOWN
